<?xml version="1.0" encoding="UTF-8"?>
<objects serializationModel="Studio.02.00.00">
	<object class="EncodingSetting" id="{ee82fa62-3391-49b3-909d-da6936611e42}">
		<property name="encodingFormat">
			<value>3</value>
		</property>
		<property name="quality">
			<value>37</value>
		</property>
		<relationship name="platform">
			<destination>{49fd8fa2-7518-4e23-b2f2-ee50a033dd10}</destination>
		</relationship>
		<relationship name="encodable">
			<destination>{036be2d4-6049-4550-852d-83fd853a91c8}</destination>
		</relationship>
	</object>
</objects>
